open3d_azure_kinect_ubuntu1604_fix/__init__.py
open3d_azure_kinect_ubuntu1604_fix/libdepthengine.so
open3d_azure_kinect_ubuntu1604_fix/libk4a.so
open3d_azure_kinect_ubuntu1604_fix/libk4arecord.so
open3d_azure_kinect_ubuntu1604_fix/libstdc++.so
open3d_azure_kinect_ubuntu1604_fix/include/k4a/k4a.h
open3d_azure_kinect_ubuntu1604_fix/include/k4a/k4a.hpp
open3d_azure_kinect_ubuntu1604_fix/include/k4a/k4a_export.h
open3d_azure_kinect_ubuntu1604_fix/include/k4a/k4atypes.h
open3d_azure_kinect_ubuntu1604_fix/include/k4a/k4aversion.h
open3d_azure_kinect_ubuntu1604_fix/include/k4arecord/k4arecord_export.h
open3d_azure_kinect_ubuntu1604_fix/include/k4arecord/playback.h
open3d_azure_kinect_ubuntu1604_fix/include/k4arecord/playback.hpp
open3d_azure_kinect_ubuntu1604_fix/include/k4arecord/record.h
open3d_azure_kinect_ubuntu1604_fix/include/k4arecord/types.h
open3d_azure_kinect_ubuntu1604_fix-0.2.dist-info/LICENSE
open3d_azure_kinect_ubuntu1604_fix-0.2.dist-info/METADATA
open3d_azure_kinect_ubuntu1604_fix-0.2.dist-info/WHEEL
open3d_azure_kinect_ubuntu1604_fix-0.2.dist-info/top_level.txt
open3d_azure_kinect_ubuntu1604_fix-0.2.dist-info/RECORD
